awsmailman/__init__.py
awsmailman/mailman.py
awsmailman-0.4.0.dist-info/LICENSE
awsmailman-0.4.0.dist-info/METADATA
awsmailman-0.4.0.dist-info/WHEEL
awsmailman-0.4.0.dist-info/entry_points.txt
awsmailman-0.4.0.dist-info/top_level.txt
awsmailman-0.4.0.dist-info/RECORD
