Metadata-Version: 2.1
Name: awsmailman
Version: 0.4.0
Summary: A utility for updating domain registrant information in Amazon Route 53
Home-page: https://github.com/fernando-mc/aws-mailman
Author: Fernando Medina Corey
Author-email: fernandomc.sea@gmail.com
License: MIT
Keywords: AWS,Route53,Domains
Platform: UNKNOWN
Classifier: Development Status :: 4 - Beta
Classifier: Intended Audience :: Developers
Classifier: Topic :: Software Development :: Build Tools
Classifier: License :: OSI Approved :: MIT License
Classifier: Programming Language :: Python :: 3
Classifier: Programming Language :: Python :: 3.4
Classifier: Programming Language :: Python :: 3.5
Classifier: Programming Language :: Python :: 3.6
Classifier: Programming Language :: Python :: 3.7
Classifier: Programming Language :: Python :: 3.8
License-File: LICENSE
Requires-Dist: boto3
Requires-Dist: bullet
